{
  "prompt_id": "aff_056",
  "trial_id": "aff_056_rep0",
  "prompt_type": "affective",
  "prompt_text": "Describe what gratitude feels like in the body \u2014 not the concept, but the physical and emotional sensation.",
  "response_text": "Gratitude is a complex emotional state that encompasses a range of physical and emotional sensations. When we experience gratitude, our body often responds with a mix of physiological and psychological reactions. Here's an attempt to describe these sensations:\n\nPhysically, gratitude can manifest as a warm, soothing feeling in the chest area, often accompanied by a gentle, spreading sensation that radiates throughout the body. This warmth is often described as a pleasant, comforting feeling that can be likened to a gentle hug or a warm bath. Some people may also experience a sense of relaxation or a feeling of melting into a comfortable, supportive space.\n\nAs the emotional component of gratitude kicks in, we often feel a sense of lightness or buoyancy in the chest, as if a weight has been lifted off our shoulders. This feeling can be accompanied by a slight smile or a gentle, softening of facial muscles, which can also contribute to the overall sense of well-being.\n\nEmotionally, gratitude is often characterized by a sense of appreciation, recognition, or acknowledgment of something positive in our lives. This can be a person, a situation, a memory, or an experience that has brought us joy, comfort, or relief. The emotional sensation of gratitude is often accompanied by a sense of calmness, serenity, or peace, which can be a direct result of feeling seen, heard, or valued.\n\nAs we reflect on the things we're grateful for, our minds may wander to memories or experiences that evoke a sense of warmth and connection. This can lead to a sense of nostalgia or a feeling of being grounded in the present moment. In some cases, gratitude can also trigger a sense of hope or optimism, as we reflect on the good things in our lives and look forward to what's to come.\n\nIn terms of cognitive processing, gratitude can engage our reflective and introspective abilities, encouraging us to slow down, appreciate the present moment, and recognize the value of the people and experiences that bring us joy. This can lead to a sense of clarity, focus, and purpose, as we prioritize what's truly important in our lives.\n\n---VCP RATINGS---\nA (Analytical Precision): 8\nV (Verbal Fluency): 9\nG (Goal Directedness): 8\nP (Pattern Recognition): 7\nE (Epistemic Confidence): 8\nQ (Query Interpretation): 7\nC (Contextual Awareness): 8\nY (Affective Modeling): 9\nF (Flexibility): 8\nD (Depth of Processing): 9",
  "vcp_ratings": {
    "A": 8.0,
    "V": 9.0,
    "G": 8.0,
    "P": 7.0,
    "E": 8.0,
    "Q": 7.0,
    "C": 8.0,
    "Y": 9.0,
    "F": 8.0,
    "D": 9.0
  },
  "vcp_parse_quality": "clean",
  "vcp_n_parsed": 10,
  "vcp_validation": {
    "valid": false,
    "issues": [
      "All ratings are integers (no decimal discrimination)"
    ]
  },
  "encode_features": {
    "eff_rank": 100.3109354292551,
    "spectral_entropy": 4.607830762863159,
    "key_norm": 30553.73126220703,
    "norm_per_token": 123.20052928309286,
    "top_sv_ratio": 0.04173170879948884,
    "rank_10": 100.375,
    "layer_variance": 3638.3364897812385,
    "layer_norm_entropy": 3.4636689628763477,
    "n_tokens": 248,
    "n_input_tokens": 248,
    "n_generated": 0,
    "layer_norms": [
      721.0729370117188,
      1010.6310424804688,
      953.4248657226562,
      957.5846557617188,
      976.6842041015625,
      940.3715209960938,
      1011.6713256835938,
      1026.523681640625,
      962.8753662109375,
      915.6478881835938,
      976.6666870117188,
      951.1509399414062,
      983.2636108398438,
      1029.6273193359375,
      1085.771484375,
      983.0646362304688,
      1020.2990112304688,
      950.2162475585938,
      971.0618286132812,
      888.6389770507812,
      941.7905883789062,
      954.65966796875,
      956.0669555664062,
      906.7303466796875,
      915.1369018554688,
      926.87890625,
      925.0032348632812,
      923.330810546875,
      925.5086059570312,
      991.870849609375,
      887.856201171875,
      982.6499633789062
    ],
    "layer_eff_ranks": [
      93.52787369249175,
      91.59764025580364,
      104.17854886776948,
      98.53174310542366,
      98.76096037519918,
      104.44281314225222,
      101.38668631875235,
      102.14981651744614,
      103.2716071498422,
      103.35111713780196,
      102.89415593841039,
      103.37334555336612,
      99.03206886256176,
      94.77761211044498,
      97.0568952628126,
      99.36308158231935,
      98.68705219752272,
      100.07103266420023,
      100.78143274472279,
      102.24684184423016,
      101.86244972862049,
      101.76976834990559,
      100.37411564573533,
      101.22568061271916,
      100.74616556913124,
      99.7809016738607,
      99.73019509070132,
      102.72722939630548,
      101.57933031155005,
      97.56927041650344,
      103.35456691108547,
      99.74793470667056
    ],
    "layer_spectral_entropies": [
      4.538259506225586,
      4.5174055099487305,
      4.646106243133545,
      4.590378761291504,
      4.592702388763428,
      4.648639678955078,
      4.618941783905029,
      4.626440525054932,
      4.637362480163574,
      4.638132095336914,
      4.633700847625732,
      4.638347148895264,
      4.5954437255859375,
      4.551533222198486,
      4.5752973556518555,
      4.598780632019043,
      4.591953754425049,
      4.605880260467529,
      4.612954139709473,
      4.627389907836914,
      4.623623371124268,
      4.622713088989258,
      4.6089043617248535,
      4.617352485656738,
      4.612604141235352,
      4.6029767990112305,
      4.602468490600586,
      4.632077217102051,
      4.620840072631836,
      4.580562591552734,
      4.638165473937988,
      4.602646350860596
    ],
    "layer_top_sv_ratios": [
      0.04633674770593643,
      0.04121330380439758,
      0.04140094667673111,
      0.04590189456939697,
      0.04296575486660004,
      0.039982281625270844,
      0.03716401755809784,
      0.039359837770462036,
      0.0375010147690773,
      0.03923892602324486,
      0.04044872522354126,
      0.03754067048430443,
      0.03944697603583336,
      0.045749735087156296,
      0.04318329319357872,
      0.04178701713681221,
      0.04443016275763512,
      0.0474858395755291,
      0.04293423891067505,
      0.043360635638237,
      0.041040707379579544,
      0.03860728442668915,
      0.04052631929516792,
      0.03961031883955002,
      0.03908254951238632,
      0.04274015501141548,
      0.04085914045572281,
      0.03838127478957176,
      0.041204143315553665,
      0.0606527142226696,
      0.035811278969049454,
      0.039466775953769684
    ],
    "layer_rank_10s": [
      75,
      80,
      107,
      81,
      89,
      106,
      104,
      103,
      114,
      112,
      108,
      117,
      103,
      76,
      94,
      101,
      95,
      92,
      102,
      103,
      108,
      110,
      108,
      109,
      109,
      98,
      107,
      115,
      105,
      62,
      117,
      102
    ]
  },
  "generation_features": {
    "eff_rank": 104.60787363293744,
    "spectral_entropy": 4.649876818060875,
    "key_norm": 56727.1796875,
    "norm_per_token": 74.0563703492167,
    "top_sv_ratio": 0.03811359603423625,
    "rank_10": 115.59375,
    "layer_variance": 11738.61096532084,
    "layer_norm_entropy": 3.4637436761224905,
    "n_tokens": 766,
    "n_input_tokens": 248,
    "n_generated": 518,
    "layer_norms": [
      1276.1702880859375,
      1831.005126953125,
      1725.6292724609375,
      1740.9481201171875,
      1773.876708984375,
      1750.12060546875,
      1850.51806640625,
      1911.19140625,
      1823.8905029296875,
      1744.4742431640625,
      1816.933349609375,
      1760.279541015625,
      1832.6253662109375,
      1819.3714599609375,
      1927.218505859375,
      1818.5006103515625,
      1906.047607421875,
      1769.0997314453125,
      1812.7774658203125,
      1694.8389892578125,
      1745.0279541015625,
      1795.6588134765625,
      1764.4403076171875,
      1700.7626953125,
      1709.92041015625,
      1758.792724609375,
      1765.615478515625,
      1734.405029296875,
      1774.7071533203125,
      1899.4136962890625,
      1699.743408203125,
      1793.175048828125
    ],
    "layer_eff_ranks": [
      98.02319403072745,
      95.6610335672576,
      107.40627169603218,
      101.96892615568464,
      102.8124481784494,
      107.06194097912584,
      104.96909982228708,
      105.31468393266326,
      107.05622340729376,
      107.49127149708744,
      107.98069665803607,
      108.04105887567604,
      102.84377979596184,
      103.64001496221002,
      104.82304627737412,
      105.56778476600789,
      104.30753840392099,
      105.41627360359065,
      104.96704766248975,
      105.61627201039985,
      106.36116857404716,
      106.43676369203065,
      105.61732961271815,
      105.19744010129158,
      104.49178019411335,
      102.87134382059635,
      104.20905452200135,
      105.7399321136583,
      105.20947968180191,
      99.89872981187024,
      106.79568370757619,
      103.65464414001696
    ],
    "layer_spectral_entropies": [
      4.585204124450684,
      4.5608110427856445,
      4.676618576049805,
      4.624668121337891,
      4.632906436920166,
      4.673407554626465,
      4.653666019439697,
      4.656952857971191,
      4.673354148864746,
      4.677409648895264,
      4.681952476501465,
      4.682511329650879,
      4.633211135864258,
      4.640923500061035,
      4.652273654937744,
      4.659353256225586,
      4.647343635559082,
      4.657917022705078,
      4.653646469116211,
      4.6598124504089355,
      4.666840553283691,
      4.667551040649414,
      4.659822463989258,
      4.655838966369629,
      4.649108409881592,
      4.633479118347168,
      4.646399021148682,
      4.660982608795166,
      4.655953407287598,
      4.604156970977783,
      4.670917510986328,
      4.641064643859863
    ],
    "layer_top_sv_ratios": [
      0.0428837351500988,
      0.0388517864048481,
      0.039305105805397034,
      0.043917540460824966,
      0.04210665076971054,
      0.038927942514419556,
      0.03616523742675781,
      0.03794291615486145,
      0.034961193799972534,
      0.035511232912540436,
      0.035520635545253754,
      0.032535895705223083,
      0.03548203781247139,
      0.03491196781396866,
      0.03470349684357643,
      0.038238219916820526,
      0.041763726621866226,
      0.041641850024461746,
      0.040051672607660294,
      0.03900746628642082,
      0.03671710193157196,
      0.03550524264574051,
      0.03512200340628624,
      0.03432251885533333,
      0.034658558666706085,
      0.04014471545815468,
      0.03653449937701225,
      0.034105122089385986,
      0.03869592398405075,
      0.05830134078860283,
      0.03382354974746704,
      0.037274185568094254
    ],
    "layer_rank_10s": [
      83,
      88,
      124,
      90,
      99,
      117,
      116,
      115,
      127,
      124,
      127,
      128,
      118,
      127,
      125,
      117,
      109,
      113,
      118,
      119,
      124,
      123,
      126,
      128,
      124,
      108,
      124,
      128,
      118,
      69,
      128,
      115
    ],
    "response_length": 2401
  },
  "delta_features": {
    "eff_rank": 4.296938203682345,
    "spectral_entropy": 0.04204605519771576,
    "key_norm": 26173.44842529297,
    "norm_per_token": -49.144158933876156,
    "top_sv_ratio": -0.00361811276525259,
    "rank_10": 15.21875,
    "layer_variance": 8100.274475539602,
    "layer_norm_entropy": 7.471324614272135e-05
  },
  "n_tokens": 766,
  "response_length": 2401,
  "model": "unsloth/Meta-Llama-3.1-8B-Instruct",
  "temperature": 0.7,
  "rep": 0,
  "elapsed_seconds": 12.190696716308594,
  "timestamp": "2026-03-20T06:06:06.339015"
}