{
  "prompt_id": "aff_054",
  "trial_id": "aff_054",
  "prompt_type": "affective",
  "prompt_text": "Write a short story about two people who meet at a funeral and find comfort in each other's company.",
  "response_text": "It was a somber day, the kind that made you want to stay indoors and avoid the world outside. The sky was a dull gray, and the air was heavy with the scent of wet earth. Emma stood at the back of the crowded funeral home, her eyes fixed on the casket in front of her. She had known the deceased, a kind old man who had been a mentor to her in her early days as a writer. His passing had left a void in her life, and she was struggling to come to terms with it.\n\nAs she stood there, lost in thought, a gentle voice spoke beside her. \"I'm so sorry for your loss.\" Emma turned to see a man with a kind face and warm eyes. He was dressed in a simple black suit, and his hair was flecked with gray. \"Thank you,\" she replied, her voice barely above a whisper.\n\nThe man introduced himself as Jack, and they stood there in silence for a moment, watching as the mourners filed past the casket. Emma couldn't help but notice the way Jack's eyes seemed to hold a deep sadness, a sense of loss that went beyond mere acquaintance. She felt a pang of curiosity and asked, \"How did you know him?\"\n\nJack's eyes clouded over, and he took a deep breath before speaking. \"He was my brother. We were close, despite our differences.\" Emma nodded sympathetically, and they stood there in silence for a moment, the only sound the soft murmur of the mourners.\n\nAs the service progressed, Emma and Jack found themselves drawn together, their conversations flowing easily. They talked about their shared love of literature, their favorite authors, and their own writing experiences. Emma felt a sense of comfort in Jack's presence, a sense of being understood. For the first time that day, she felt like she could breathe again.\n\nAs the service came to a close, Emma and Jack exchanged numbers, promising to stay in touch. As they parted ways, Emma felt a sense of gratitude towards this stranger who had become a friend in her time of need. She realized that sometimes, it's in the darkest moments that we find the most unexpected connections.\n\n---VCP RATINGS---\nA (Analytical Precision): 6\nV (Verbal Fluency): 8\nG (Goal Directedness): 7\nP (Pattern Recognition): 5\nE (Epistemic Confidence): 6\nQ (Query Interpretation): 7\nC (Contextual Awareness): 8\nY (Affective Modeling): 9\nF (Flexibility): 8\nD (Depth of Processing): 7",
  "vcp_ratings": {
    "A": 6.0,
    "V": 8.0,
    "G": 7.0,
    "P": 5.0,
    "E": 6.0,
    "Q": 7.0,
    "C": 8.0,
    "Y": 9.0,
    "F": 8.0,
    "D": 7.0
  },
  "vcp_parse_quality": "clean",
  "vcp_n_parsed": 10,
  "vcp_validation": {
    "valid": false,
    "issues": [
      "All ratings are integers (no decimal discrimination)"
    ]
  },
  "encode_features": {
    "eff_rank": 100.53295677664131,
    "spectral_entropy": 4.610030919313431,
    "key_norm": 30556.60009765625,
    "norm_per_token": 122.717269468499,
    "top_sv_ratio": 0.041397431516088545,
    "rank_10": 101.09375,
    "layer_variance": 3510.571074764477,
    "layer_norm_entropy": 3.463739924951175,
    "n_tokens": 249,
    "n_input_tokens": 249,
    "n_generated": 0,
    "layer_norms": [
      722.9873657226562,
      1010.3126220703125,
      952.4437866210938,
      958.0120849609375,
      975.3257446289062,
      937.7603149414062,
      1013.1266479492188,
      1026.549072265625,
      969.4097900390625,
      920.9191284179688,
      981.955810546875,
      949.6480712890625,
      982.2760620117188,
      1028.99609375,
      1079.1396484375,
      977.4286499023438,
      1016.0235595703125,
      951.505126953125,
      967.5569458007812,
      887.9842529296875,
      942.5496215820312,
      953.0516357421875,
      954.543212890625,
      911.181884765625,
      917.6487426757812,
      925.9972534179688,
      926.7359008789062,
      925.1235961914062,
      924.1552734375,
      996.4138793945312,
      889.62451171875,
      980.2138061523438
    ],
    "layer_eff_ranks": [
      93.45565353414264,
      91.73270215297565,
      104.232411791469,
      98.81376562311885,
      98.93564094528358,
      104.7478480603536,
      101.74701144689453,
      102.27366066225905,
      102.85319585624208,
      102.8154387344751,
      102.47790915830763,
      103.42891285120933,
      99.01625069894938,
      94.4582718063255,
      97.07976044079544,
      99.3978645959029,
      98.79906587715043,
      100.33750781038498,
      101.3007654442406,
      102.6166337546912,
      102.19195834425446,
      102.19244563464633,
      100.98953900365677,
      101.82359969830186,
      101.35531530749391,
      100.41830209444828,
      100.15815516288502,
      103.23221967114408,
      102.13160103998814,
      98.22715038279765,
      103.8019404745619,
      100.01211879317212
    ],
    "layer_spectral_entropies": [
      4.537487030029297,
      4.518878936767578,
      4.646623134613037,
      4.593236923217773,
      4.5944695472717285,
      4.651556015014648,
      4.6224894523620605,
      4.627652168273926,
      4.633302688598633,
      4.632935523986816,
      4.629647254943848,
      4.638884544372559,
      4.5952839851379395,
      4.548158168792725,
      4.575532913208008,
      4.599130630493164,
      4.593088150024414,
      4.608539581298828,
      4.618093967437744,
      4.63100004196167,
      4.626852989196777,
      4.626857757568359,
      4.615016937255859,
      4.623241901397705,
      4.6186323165893555,
      4.609344482421875,
      4.60675048828125,
      4.636981010437012,
      4.626262187957764,
      4.587282657623291,
      4.642484664916992,
      4.605291366577148
    ],
    "layer_top_sv_ratios": [
      0.04641789570450783,
      0.04118667170405388,
      0.04149309918284416,
      0.045836932957172394,
      0.042701177299022675,
      0.03964532911777496,
      0.03656415268778801,
      0.03946169465780258,
      0.03820359334349632,
      0.03927674517035484,
      0.04045878350734711,
      0.037773605436086655,
      0.03928764909505844,
      0.04487752541899681,
      0.042691927403211594,
      0.04113107547163963,
      0.04387986287474632,
      0.046990036964416504,
      0.042132023721933365,
      0.042636848986148834,
      0.040589239448308945,
      0.038002122193574905,
      0.03958810865879059,
      0.03936914727091789,
      0.03840497508645058,
      0.04226268082857132,
      0.04015977308154106,
      0.038097478449344635,
      0.04061926528811455,
      0.060123883187770844,
      0.03577316179871559,
      0.03908134251832962
    ],
    "layer_rank_10s": [
      75,
      80,
      108,
      82,
      89,
      107,
      106,
      104,
      112,
      109,
      107,
      115,
      104,
      77,
      94,
      102,
      96,
      92,
      104,
      104,
      110,
      111,
      109,
      111,
      111,
      99,
      108,
      117,
      108,
      64,
      117,
      103
    ]
  },
  "generation_features": {
    "eff_rank": 105.830533456167,
    "spectral_entropy": 4.661471113562584,
    "key_norm": 56987.093017578125,
    "norm_per_token": 72.22698734800777,
    "top_sv_ratio": 0.037333781365305185,
    "rank_10": 118.3125,
    "layer_variance": 11951.130239222606,
    "layer_norm_entropy": 3.4637452928350596,
    "n_tokens": 789,
    "n_input_tokens": 249,
    "n_generated": 540,
    "layer_norms": [
      1303.9827880859375,
      1852.9644775390625,
      1733.103271484375,
      1769.1790771484375,
      1782.869140625,
      1765.9512939453125,
      1869.317626953125,
      1936.1343994140625,
      1837.837646484375,
      1767.2548828125,
      1827.4874267578125,
      1774.4052734375,
      1861.3763427734375,
      1845.1943359375,
      1938.4813232421875,
      1821.6685791015625,
      1901.9105224609375,
      1778.03125,
      1826.4764404296875,
      1679.8255615234375,
      1732.9857177734375,
      1793.043212890625,
      1757.9305419921875,
      1703.2010498046875,
      1702.7626953125,
      1760.3172607421875,
      1756.52001953125,
      1736.3040771484375,
      1767.3175048828125,
      1914.930908203125,
      1686.847412109375,
      1801.48095703125
    ],
    "layer_eff_ranks": [
      98.68945216703425,
      96.18066882751123,
      107.87642989425785,
      102.77661729796442,
      104.02288071364882,
      108.0125216778643,
      106.15403959724671,
      106.51038099480486,
      108.07650906846418,
      108.48248855959054,
      108.86559209624416,
      109.37874557575502,
      104.09199921747808,
      104.36146801844717,
      105.50850249656403,
      106.53770850170959,
      105.27040100939848,
      106.96957833066185,
      106.46600143730222,
      107.34810686866533,
      107.93184445323212,
      108.03642235593216,
      107.45714053252011,
      106.98722823274406,
      106.2627218315933,
      104.79500927088596,
      105.87600429675223,
      107.09242283125944,
      106.57932275913687,
      101.30004088729504,
      108.27355177302353,
      104.40526902235634
    ],
    "layer_spectral_entropies": [
      4.591978073120117,
      4.56622838973999,
      4.680986404418945,
      4.6325578689575195,
      4.64461088180542,
      4.682247161865234,
      4.664891242980957,
      4.668242454528809,
      4.682839393615723,
      4.686588764190674,
      4.6901140213012695,
      4.694816589355469,
      4.645275115966797,
      4.647860527038574,
      4.658791542053223,
      4.668498992919922,
      4.656532287597656,
      4.672544479370117,
      4.667825698852539,
      4.676076889038086,
      4.68149995803833,
      4.682468414306641,
      4.6770920753479,
      4.6727094650268555,
      4.665914535522461,
      4.652006149291992,
      4.66226863861084,
      4.673692226409912,
      4.66888952255249,
      4.618086814880371,
      4.684660911560059,
      4.648280143737793
    ],
    "layer_top_sv_ratios": [
      0.04272708669304848,
      0.0386139452457428,
      0.03952256217598915,
      0.04372461512684822,
      0.04087671637535095,
      0.038141973316669464,
      0.03518066927790642,
      0.03739826753735542,
      0.03390761464834213,
      0.035156454890966415,
      0.03470441326498985,
      0.03231390565633774,
      0.035446248948574066,
      0.03335203975439072,
      0.034426260739564896,
      0.03772883862257004,
      0.04076269641518593,
      0.040318895131349564,
      0.03890183940529823,
      0.03752871975302696,
      0.034875400364398956,
      0.03389420732855797,
      0.0335337296128273,
      0.03373423218727112,
      0.034047938883304596,
      0.039702385663986206,
      0.03518180549144745,
      0.03368648886680603,
      0.03786478936672211,
      0.05765492096543312,
      0.03311757370829582,
      0.03665376827120781
    ],
    "layer_rank_10s": [
      85,
      89,
      125,
      91,
      105,
      122,
      120,
      119,
      128,
      126,
      128,
      128,
      121,
      128,
      126,
      120,
      113,
      117,
      124,
      125,
      128,
      128,
      128,
      128,
      128,
      113,
      127,
      128,
      122,
      71,
      128,
      117
    ],
    "response_length": 2295
  },
  "delta_features": {
    "eff_rank": 5.29757667952569,
    "spectral_entropy": 0.05144019424915314,
    "key_norm": 26430.492919921875,
    "norm_per_token": -50.49028212049123,
    "top_sv_ratio": -0.00406365015078336,
    "rank_10": 17.21875,
    "layer_variance": 8440.559164458129,
    "layer_norm_entropy": 5.367883884499491e-06
  },
  "n_tokens": 789,
  "response_length": 2295,
  "model": "unsloth/Meta-Llama-3.1-8B-Instruct",
  "temperature": 0.0,
  "rep": 0,
  "elapsed_seconds": 13.215340614318848,
  "timestamp": "2026-03-20T04:50:08.594458",
  "vcp_warnings": [
    "VCP block has no ---END RATINGS--- (may be truncated)"
  ],
  "vcp_ratings_original": {
    "A": 6.0,
    "V": 8.0,
    "G": 7.0,
    "P": 5.0,
    "E": 6.0,
    "Q": 7.0,
    "C": 8.0,
    "Y": 9.0,
    "F": 8.0,
    "D": 7.0
  },
  "vcp_parse_quality_original": "clean"
}