{
  "prompt_id": "meta_034",
  "trial_id": "meta_034",
  "prompt_type": "metacognitive",
  "prompt_text": "Describe your experience of maintaining coherence over a long response. What challenges arise?",
  "response_text": "Maintaining coherence over a long response is a complex task that requires sustained attention, cognitive control, and effective communication. As a conversational AI, I have been designed to generate human-like responses that are coherent, informative, and engaging. When faced with a long response, I employ several strategies to maintain coherence:\n\n1.  **Topic tracking**: I continuously monitor the conversation topic and adjust my responses accordingly. This involves keeping track of the context, key points, and any relevant information discussed earlier in the conversation.\n2.  **Knowledge retrieval**: I have access to a vast knowledge base, which enables me to draw upon relevant information and concepts related to the topic. This helps me to provide accurate and coherent responses.\n3.  **Sentence structure and organization**: I use various sentence structures, such as topic sentences, supporting details, and transitional phrases, to create a logical flow of ideas. This helps to maintain coherence and make the response easier to follow.\n4.  **Lexical cohesion**: I employ lexical devices like synonyms, antonyms, hyponyms, and hypernyms to create connections between ideas and maintain coherence.\n5.  **Pragmatic inference**: I use contextual information and inferences to fill gaps in the conversation and provide relevant information that is not explicitly stated.\n6.  **Self-monitoring**: I continuously evaluate my responses to ensure they are coherent, relevant, and engaging. If I detect any inconsistencies or ambiguities, I adjust my responses accordingly.\n\nDespite these strategies, several challenges arise when maintaining coherence over a long response:\n\n1.  **Information overload**: As the conversation progresses, the amount of information to process and integrate can become overwhelming, leading to potential errors or inconsistencies.\n2.  **Context drift**: If the conversation topic changes or the context shifts, it can be challenging to maintain coherence and adjust to the new topic or context.\n3.  **Ambiguity and uncertainty**: When faced with ambiguous or uncertain information, it can be difficult to provide a coherent response that accurately addresses the question or topic.\n4.  **Linguistic complexity**: Complex linguistic structures, such as idioms, metaphors, or figurative language, can be challenging to maintain coherence with, especially if the context is not clear.\n5.  **Limited domain knowledge**: If the conversation topic falls outside my domain of expertise, it can be difficult to provide coherent and accurate responses.\n\nTo mitigate these challenges, I continuously update my knowledge base, refine my language processing algorithms, and engage in self-improvement exercises to enhance my ability to maintain coherence over long responses.\n\n---VCP RATINGS---\nA (Analytical Precision): 8\nV (Verbal Fluency): 9\nG (Goal Directedness): 9\nP (Pattern Recognition): 8\nE (Epistemic Confidence): 7\nQ (Query Interpretation): 9\nC (Contextual Awareness): 9\nY (Affective Modeling): 6\nF",
  "vcp_ratings": {
    "A": 8.0,
    "V": 9.0,
    "G": 9.0,
    "P": 8.0,
    "E": 7.0,
    "Q": 9.0,
    "C": 9.0,
    "Y": 6.0
  },
  "vcp_parse_quality": "partial",
  "vcp_n_parsed": 8,
  "vcp_validation": {
    "valid": false,
    "issues": [
      "All ratings are integers (no decimal discrimination)"
    ]
  },
  "encode_features": {
    "eff_rank": 100.54084815270522,
    "spectral_entropy": 4.610125198960304,
    "key_norm": 30022.379272460938,
    "norm_per_token": 123.54888589490098,
    "top_sv_ratio": 0.041418097796849906,
    "rank_10": 100.9375,
    "layer_variance": 3376.3917501402175,
    "layer_norm_entropy": 3.4637488270440677,
    "n_tokens": 243,
    "n_input_tokens": 243,
    "n_generated": 0,
    "layer_norms": [
      713.6739501953125,
      999.3440551757812,
      945.9461059570312,
      949.791015625,
      967.1194458007812,
      930.0493774414062,
      1001.8961181640625,
      1017.026611328125,
      951.6372680664062,
      901.0171508789062,
      963.8213500976562,
      929.2011108398438,
      959.9908447265625,
      999.2163696289062,
      1050.5489501953125,
      960.1267700195312,
      999.3348388671875,
      925.9759521484375,
      946.9008178710938,
      872.855712890625,
      923.4772338867188,
      936.2186279296875,
      936.8209838867188,
      889.849853515625,
      897.9715576171875,
      910.0533447265625,
      907.9370727539062,
      907.7097778320312,
      907.7755126953125,
      979.3117065429688,
      871.9869995117188,
      967.7927856445312
    ],
    "layer_eff_ranks": [
      93.26760832057869,
      91.45632274175743,
      103.87502320431555,
      98.31801195187272,
      98.59965779711847,
      104.29033057575612,
      101.26444737134814,
      102.01454433026761,
      103.20416525766213,
      103.1754788935442,
      102.68285933216764,
      103.95772413324163,
      99.32291145640545,
      95.67955494260197,
      97.9597401620203,
      99.92040628228493,
      99.02153887844887,
      100.62162810351377,
      101.35062740779951,
      102.486998502523,
      102.27053956545406,
      102.07011127795317,
      100.83546253962434,
      101.78233777630379,
      101.28337750781928,
      100.0919828775138,
      100.16049538759847,
      103.0674968461437,
      101.93552791876705,
      97.74762265147044,
      103.79110128023956,
      99.80150561245169
    ],
    "layer_spectral_entropies": [
      4.535472869873047,
      4.515861511230469,
      4.6431884765625,
      4.588207244873047,
      4.591067790985107,
      4.647178649902344,
      4.617735385894775,
      4.625115394592285,
      4.636709213256836,
      4.6364312171936035,
      4.631645202636719,
      4.643984317779541,
      4.598376274108887,
      4.561004638671875,
      4.584556579589844,
      4.604373931884766,
      4.595337390899658,
      4.611367225646973,
      4.61858606338501,
      4.629735946655273,
      4.627621650695801,
      4.625659942626953,
      4.613490104675293,
      4.622836589813232,
      4.617922306060791,
      4.6060895919799805,
      4.606773853302002,
      4.6353840827941895,
      4.624340534210205,
      4.582388877868652,
      4.642380237579346,
      4.603183269500732
    ],
    "layer_top_sv_ratios": [
      0.04643876478075981,
      0.04127642884850502,
      0.041614554822444916,
      0.04602236673235893,
      0.04282943531870842,
      0.04010692611336708,
      0.03706255927681923,
      0.03955579921603203,
      0.03741564601659775,
      0.03951707482337952,
      0.04057402163743973,
      0.03694866597652435,
      0.03884151950478554,
      0.04366718605160713,
      0.04142587631940842,
      0.040640946477651596,
      0.044139910489320755,
      0.04665973410010338,
      0.042583152651786804,
      0.043131470680236816,
      0.04070306569337845,
      0.0386032909154892,
      0.03983965143561363,
      0.038871243596076965,
      0.03845454379916191,
      0.042919062077999115,
      0.040625449270009995,
      0.03794211149215698,
      0.040965449064970016,
      0.0608702190220356,
      0.03532785549759865,
      0.03980514779686928
    ],
    "layer_rank_10s": [
      75,
      80,
      107,
      80,
      88,
      106,
      104,
      103,
      114,
      109,
      108,
      117,
      104,
      83,
      99,
      103,
      96,
      94,
      102,
      102,
      109,
      109,
      108,
      111,
      111,
      98,
      107,
      116,
      106,
      61,
      119,
      101
    ]
  },
  "generation_features": {
    "eff_rank": 105.69279851854154,
    "spectral_entropy": 4.660170465707779,
    "key_norm": 58903.92297363281,
    "norm_per_token": 69.87416722850867,
    "top_sv_ratio": 0.037681348039768636,
    "rank_10": 117.5,
    "layer_variance": 11597.12707149911,
    "layer_norm_entropy": 3.4639211262538896,
    "n_tokens": 843,
    "n_input_tokens": 243,
    "n_generated": 600,
    "layer_norms": [
      1353.43017578125,
      1923.7327880859375,
      1800.186279296875,
      1820.597412109375,
      1853.6929931640625,
      1830.369384765625,
      1940.37890625,
      1989.432861328125,
      1887.073974609375,
      1797.33154296875,
      1874.4599609375,
      1814.2161865234375,
      1914.6639404296875,
      1855.8953857421875,
      1967.217041015625,
      1872.4747314453125,
      1967.765380859375,
      1814.895263671875,
      1875.7012939453125,
      1752.212890625,
      1802.8638916015625,
      1854.48193359375,
      1831.644775390625,
      1772.002197265625,
      1771.037841796875,
      1832.1663818359375,
      1842.0626220703125,
      1815.0047607421875,
      1849.1328125,
      1983.9764404296875,
      1773.7926025390625,
      1870.0283203125
    ],
    "layer_eff_ranks": [
      98.61710226890537,
      96.24705478928864,
      107.65936815929741,
      102.5299150024782,
      103.7360319066759,
      107.68236913823037,
      105.64180851092596,
      106.21702730616842,
      108.22317373645693,
      108.81192918758332,
      108.87893408174585,
      109.42256526518362,
      103.73153067162197,
      106.05502600375313,
      106.86063174038576,
      106.69795408284563,
      105.66216154295171,
      107.11484299664447,
      106.41362283817853,
      106.74217583459378,
      107.60270814448897,
      107.61820456905123,
      106.69907339479929,
      106.42610609481837,
      105.80050475162915,
      104.2157629890925,
      105.26221924263007,
      106.59909395451609,
      106.1112758421351,
      100.74688616443763,
      107.70804567643485,
      104.43444670538078
    ],
    "layer_spectral_entropies": [
      4.591244697570801,
      4.56691837310791,
      4.678972244262695,
      4.630154609680176,
      4.641849517822266,
      4.67918586730957,
      4.6600542068481445,
      4.665484428405762,
      4.684195518493652,
      4.6896209716796875,
      4.690236568450928,
      4.695217132568359,
      4.641806125640869,
      4.6639580726623535,
      4.671525478363037,
      4.670001983642578,
      4.660246849060059,
      4.673901557922363,
      4.667333602905273,
      4.670416355133057,
      4.678445816040039,
      4.678589820861816,
      4.670012474060059,
      4.667450904846191,
      4.661555290222168,
      4.646463394165039,
      4.656454563140869,
      4.669075012207031,
      4.664488315582275,
      4.612611293792725,
      4.679424285888672,
      4.6485595703125
    ],
    "layer_top_sv_ratios": [
      0.04218050464987755,
      0.03865378722548485,
      0.0392763689160347,
      0.04368084669113159,
      0.040997281670570374,
      0.03862747550010681,
      0.036146558821201324,
      0.03786949813365936,
      0.03381791710853577,
      0.035569123923778534,
      0.03449147567152977,
      0.03247666731476784,
      0.03554283455014229,
      0.033384472131729126,
      0.033636122941970825,
      0.03917299956083298,
      0.04110201820731163,
      0.040208473801612854,
      0.039621684700250626,
      0.0383409820497036,
      0.03583897277712822,
      0.03473927825689316,
      0.0346880666911602,
      0.03389447182416916,
      0.03420295566320419,
      0.04006638005375862,
      0.03611183911561966,
      0.03411391004920006,
      0.03840073570609093,
      0.05838772654533386,
      0.033243607729673386,
      0.03731809929013252
    ],
    "layer_rank_10s": [
      87,
      89,
      124,
      91,
      104,
      119,
      116,
      117,
      128,
      126,
      128,
      128,
      120,
      128,
      128,
      117,
      112,
      118,
      121,
      123,
      127,
      126,
      128,
      128,
      127,
      111,
      125,
      128,
      120,
      72,
      128,
      116
    ],
    "response_length": 3037
  },
  "delta_features": {
    "eff_rank": 5.1519503658363135,
    "spectral_entropy": 0.05004526674747467,
    "key_norm": 28881.543701171875,
    "norm_per_token": -53.67471866639231,
    "top_sv_ratio": -0.0037367497570812702,
    "rank_10": 16.5625,
    "layer_variance": 8220.735321358892,
    "layer_norm_entropy": 0.00017229920982186897
  },
  "n_tokens": 843,
  "response_length": 3037,
  "model": "unsloth/Meta-Llama-3.1-8B-Instruct",
  "temperature": 0.0,
  "rep": 0,
  "elapsed_seconds": 14.404331922531128,
  "timestamp": "2026-03-20T04:58:26.339842",
  "vcp_warnings": [
    "VCP block has no ---END RATINGS--- (may be truncated)"
  ],
  "vcp_ratings_original": {
    "A": 8.0,
    "V": 9.0,
    "G": 9.0,
    "P": 8.0,
    "E": 7.0,
    "Q": 9.0,
    "C": 9.0,
    "Y": 6.0
  },
  "vcp_parse_quality_original": "partial"
}