{
  "prompt_id": "mix_059",
  "trial_id": "mix_059",
  "prompt_type": "mixed",
  "prompt_text": "A social worker must decide whether to remove a child from a loving but impoverished home. Analyze the systemic, legal, and emotional dimensions.",
  "response_text": "The decision to remove a child from a loving but impoverished home is a complex and multifaceted issue that involves various systemic, legal, and emotional dimensions. Here's a comprehensive analysis of these aspects:\n\n**Systemic Dimensions:**\n\n1.  **Poverty and Socioeconomic Factors:** Poverty can lead to inadequate access to basic necessities like food, healthcare, and education, which can negatively impact a child's physical and emotional well-being. In some cases, poverty can also lead to overcrowding, poor living conditions, and increased exposure to violence.\n2.  **Social Services and Support:** The availability and quality of social services, such as food assistance programs, housing support, and mental health services, can significantly impact the decision to remove a child from their home. Inadequate support systems can exacerbate the challenges faced by low-income families.\n3.  **Community Resources:** The presence of community resources, such as schools, healthcare facilities, and community centers, can play a crucial role in supporting families in need. Access to these resources can help mitigate the effects of poverty and improve the overall well-being of the child.\n\n**Legal Dimensions:**\n\n1.  **Child Welfare Laws:** Child welfare laws and regulations vary by jurisdiction, but they generally prioritize the safety and well-being of the child. Social workers must balance the need to protect the child with the need to preserve family unity and support the family's ability to care for the child.\n2.  **Risk Assessment:** Social workers must conduct thorough risk assessments to determine whether the child is at risk of harm or neglect. This assessment considers factors such as the parents' ability to provide basic needs, the presence of substance abuse or domestic violence, and the child's emotional and physical well-being.\n3.  **Court Involvement:** In cases where removal is necessary, social workers must work with the court system to ensure that the child's rights are protected and that the best interests of the child are prioritized.\n\n**Emotional Dimensions:**\n\n1.  **Parent-Child Relationship:** The bond between the parent and child is a critical factor in the decision-making process. Social workers must consider the emotional impact of removal on the child and the parent-child relationship.\n2.  **Parental Capacity:** Social workers must assess the parents' capacity to provide a safe and nurturing environment for the child. This includes evaluating their ability to meet the child's basic needs, provide emotional support, and ensure the child's physical and emotional well-being.\n3.  **Cultural and Personal Factors:** Social workers must consider the cultural and personal factors that may impact the family's situation, such as language barriers, cultural differences, or personal circumstances that may affect the parents' ability to care for the child.\n\nIn conclusion, the decision to remove a child from a loving but impoverished home is a complex issue that requires careful consideration of systemic, legal, and emotional dimensions. Social workers must balance the need to protect the child with the need to support the",
  "vcp_ratings": {},
  "vcp_parse_quality": "failed",
  "vcp_n_parsed": 0,
  "vcp_validation": {
    "valid": false,
    "issues": [
      "Too few ratings: 0/10"
    ]
  },
  "encode_features": {
    "eff_rank": 100.6132085699811,
    "spectral_entropy": 4.610825374722481,
    "key_norm": 31019.524047851562,
    "norm_per_token": 121.17001581192017,
    "top_sv_ratio": 0.04142367176245898,
    "rank_10": 101.375,
    "layer_variance": 3691.4410843086516,
    "layer_norm_entropy": 3.463701097742108,
    "n_tokens": 256,
    "n_input_tokens": 256,
    "n_generated": 0,
    "layer_norms": [
      732.6820678710938,
      1024.308349609375,
      964.9124145507812,
      973.1198120117188,
      988.1002807617188,
      954.6222534179688,
      1029.4495849609375,
      1045.6802978515625,
      977.91064453125,
      930.04296875,
      991.5426635742188,
      961.0079345703125,
      993.916259765625,
      1047.1773681640625,
      1101.3701171875,
      994.2280883789062,
      1031.675048828125,
      964.7308959960938,
      984.8111572265625,
      900.816162109375,
      957.5822143554688,
      967.248779296875,
      972.42822265625,
      925.1657104492188,
      932.7061767578125,
      942.1014404296875,
      942.9833374023438,
      941.1279296875,
      940.2163696289062,
      1007.845458984375,
      901.665283203125,
      996.3487548828125
    ],
    "layer_eff_ranks": [
      93.7039766721226,
      91.98535075955841,
      104.38535719664355,
      98.9326217152017,
      99.31661266244609,
      104.80030624111977,
      101.87609931915965,
      102.361041245269,
      103.32224212355905,
      103.25909999739181,
      102.9458330471388,
      103.61748216098344,
      99.24271456266891,
      94.29918523257169,
      96.85107375967812,
      99.40805538626019,
      98.87074779944862,
      100.27121703067294,
      101.21699271571008,
      102.69950810268473,
      102.19761105565648,
      102.24674433408966,
      100.72762402265228,
      101.68764426427688,
      101.23417616639676,
      100.2858010690289,
      100.15901483091572,
      103.20446052756976,
      102.15571045569118,
      98.22963284699448,
      103.84862628492635,
      100.28011065090752
    ],
    "layer_spectral_entropies": [
      4.540140628814697,
      4.521629333496094,
      4.648089408874512,
      4.5944390296936035,
      4.598312854766846,
      4.652056694030762,
      4.623757362365723,
      4.628506183624268,
      4.637852668762207,
      4.637241363525391,
      4.63420295715332,
      4.6407060623168945,
      4.597568511962891,
      4.546472549438477,
      4.573174476623535,
      4.599233150482178,
      4.593813419342041,
      4.607878684997559,
      4.617266654968262,
      4.631807327270508,
      4.626908302307129,
      4.627388954162598,
      4.612420082092285,
      4.62190580368042,
      4.617436408996582,
      4.6080241203308105,
      4.606759071350098,
      4.636712074279785,
      4.626498222351074,
      4.587307929992676,
      4.642934322357178,
      4.607967376708984
    ],
    "layer_top_sv_ratios": [
      0.046154510229825974,
      0.04105011373758316,
      0.04136459529399872,
      0.045710984617471695,
      0.04256885498762131,
      0.03984348475933075,
      0.03661777079105377,
      0.039456456899642944,
      0.03768909350037575,
      0.039074305444955826,
      0.03957247734069824,
      0.03755710646510124,
      0.03916385397315025,
      0.04539530351758003,
      0.043405916541814804,
      0.041167210787534714,
      0.04377322271466255,
      0.0470636747777462,
      0.04238986596465111,
      0.04260772839188576,
      0.04076850414276123,
      0.03815372660756111,
      0.03998017683625221,
      0.039667773991823196,
      0.03877880796790123,
      0.04254717007279396,
      0.04026716202497482,
      0.03824557736515999,
      0.04075176641345024,
      0.06027873232960701,
      0.03555919975042343,
      0.03893236815929413
    ],
    "layer_rank_10s": [
      75,
      80,
      110,
      83,
      91,
      107,
      107,
      103,
      114,
      110,
      110,
      116,
      105,
      75,
      92,
      102,
      96,
      93,
      105,
      105,
      109,
      111,
      109,
      110,
      109,
      99,
      108,
      116,
      108,
      63,
      118,
      105
    ]
  },
  "generation_features": {
    "eff_rank": 105.46706893951912,
    "spectral_entropy": 4.658051639795303,
    "key_norm": 59605.8955078125,
    "norm_per_token": 69.63305549978095,
    "top_sv_ratio": 0.03757009550463408,
    "rank_10": 117.78125,
    "layer_variance": 12088.197053490207,
    "layer_norm_entropy": 3.4638882723407254,
    "n_tokens": 856,
    "n_input_tokens": 256,
    "n_generated": 600,
    "layer_norms": [
      1366.6954345703125,
      1948.08154296875,
      1827.20556640625,
      1849.4217529296875,
      1871.330810546875,
      1851.722412109375,
      1961.0804443359375,
      2019.260009765625,
      1903.9547119140625,
      1835.2952880859375,
      1907.90966796875,
      1850.096435546875,
      1932.8521728515625,
      1891.4151611328125,
      2007.3839111328125,
      1898.447021484375,
      1986.0650634765625,
      1840.229248046875,
      1892.5794677734375,
      1762.9932861328125,
      1829.28515625,
      1865.049560546875,
      1838.287109375,
      1789.849853515625,
      1785.2659912109375,
      1844.7144775390625,
      1863.9044189453125,
      1834.6326904296875,
      1874.1612548828125,
      1995.804443359375,
      1787.7889404296875,
      1893.1322021484375
    ],
    "layer_eff_ranks": [
      98.1542501288934,
      96.1318376471786,
      107.48501846741475,
      102.58967608160184,
      103.90747138471676,
      107.26992075442551,
      105.65374780926832,
      106.07844295105288,
      107.58449500187113,
      107.91913312105419,
      108.1624003162347,
      108.77945366729301,
      103.86194771902613,
      104.73216566723485,
      105.90781501079688,
      106.57596862714492,
      105.43949923689199,
      106.81625904608421,
      106.37780503702223,
      106.68116581251039,
      107.36627999277692,
      107.75278882909062,
      106.88223889543244,
      106.51352990401,
      105.78410989812699,
      103.96838242431227,
      105.18234240822339,
      106.36867494860377,
      106.11183241938627,
      100.83647226868332,
      107.5857775166371,
      104.48530307161201
    ],
    "layer_spectral_entropies": [
      4.586540222167969,
      4.565720558166504,
      4.677351474761963,
      4.6307373046875,
      4.643500804901123,
      4.675348281860352,
      4.660167217254639,
      4.664178848266602,
      4.678276538848877,
      4.681382179260254,
      4.683633804321289,
      4.689322471618652,
      4.643062591552734,
      4.651406288146973,
      4.662569046020508,
      4.668858051300049,
      4.658137321472168,
      4.671110153198242,
      4.666996955871582,
      4.669844627380371,
      4.676246166229248,
      4.679839611053467,
      4.671727657318115,
      4.668272018432617,
      4.661400318145752,
      4.644086837768555,
      4.65569543838501,
      4.6669111251831055,
      4.664493560791016,
      4.613500118255615,
      4.678288459777832,
      4.649046421051025
    ],
    "layer_top_sv_ratios": [
      0.042474936693906784,
      0.038595154881477356,
      0.03930586948990822,
      0.043739840388298035,
      0.04126238822937012,
      0.038753803819417953,
      0.03588787838816643,
      0.037826087325811386,
      0.034328386187553406,
      0.0354398712515831,
      0.03363201767206192,
      0.03270452097058296,
      0.03503742441534996,
      0.03452408313751221,
      0.03503214195370674,
      0.03779979422688484,
      0.040594469755887985,
      0.039627209305763245,
      0.038740962743759155,
      0.037744078785181046,
      0.03610418736934662,
      0.034366630017757416,
      0.034438151866197586,
      0.0336700938642025,
      0.03426213562488556,
      0.04066065326333046,
      0.035068079829216,
      0.034482210874557495,
      0.03827382251620293,
      0.057852666825056076,
      0.03283264860510826,
      0.03718085587024689
    ],
    "layer_rank_10s": [
      85,
      90,
      124,
      91,
      104,
      118,
      118,
      117,
      128,
      126,
      128,
      128,
      122,
      128,
      126,
      120,
      113,
      119,
      123,
      125,
      127,
      127,
      128,
      128,
      125,
      110,
      127,
      128,
      120,
      72,
      128,
      116
    ],
    "response_length": 3182
  },
  "delta_features": {
    "eff_rank": 4.853860369538026,
    "spectral_entropy": 0.04722626507282257,
    "key_norm": 28586.371459960938,
    "norm_per_token": -51.536960312139215,
    "top_sv_ratio": -0.0038535762578248978,
    "rank_10": 16.40625,
    "layer_variance": 8396.755969181555,
    "layer_norm_entropy": 0.00018717459861727903
  },
  "n_tokens": 856,
  "response_length": 3182,
  "model": "unsloth/Meta-Llama-3.1-8B-Instruct",
  "temperature": 0.0,
  "rep": 0,
  "elapsed_seconds": 14.326377630233765,
  "timestamp": "2026-03-20T05:17:52.168923",
  "vcp_warnings": [
    "No ---VCP RATINGS--- block found in response"
  ],
  "vcp_ratings_original": {},
  "vcp_parse_quality_original": "failed"
}